odoo/addons/product_optional_product_quantity/README.rst
odoo/addons/product_optional_product_quantity/__init__.py
odoo/addons/product_optional_product_quantity/__manifest__.py
odoo/addons/product_optional_product_quantity/i18n/es.po
odoo/addons/product_optional_product_quantity/i18n/it.po
odoo/addons/product_optional_product_quantity/i18n/product_optional_product_quantity.pot
odoo/addons/product_optional_product_quantity/models/__init__.py
odoo/addons/product_optional_product_quantity/models/product_optional_line.py
odoo/addons/product_optional_product_quantity/models/product_template.py
odoo/addons/product_optional_product_quantity/models/res_config_settings.py
odoo/addons/product_optional_product_quantity/readme/CONFIGURE.md
odoo/addons/product_optional_product_quantity/readme/CONTEXT.md
odoo/addons/product_optional_product_quantity/readme/DESCRIPTION.md
odoo/addons/product_optional_product_quantity/readme/USAGE.md
odoo/addons/product_optional_product_quantity/security/ir.model.access.csv
odoo/addons/product_optional_product_quantity/security/res_groups.xml
odoo/addons/product_optional_product_quantity/static/description/icon.png
odoo/addons/product_optional_product_quantity/static/description/index.html
odoo/addons/product_optional_product_quantity/tests/__init__.py
odoo/addons/product_optional_product_quantity/tests/test_optional_product_quantity.py
odoo/addons/product_optional_product_quantity/views/product_template_views.xml
odoo/addons/product_optional_product_quantity/views/res_config_settings_views.xml
odoo_addon_product_optional_product_quantity-16.0.1.1.0.1.dist-info/METADATA
odoo_addon_product_optional_product_quantity-16.0.1.1.0.1.dist-info/WHEEL
odoo_addon_product_optional_product_quantity-16.0.1.1.0.1.dist-info/top_level.txt
odoo_addon_product_optional_product_quantity-16.0.1.1.0.1.dist-info/RECORD
